promypy/__init__.py
promypy/main.py
tests/__init__.py
tests/test_main.py
promypy-0.3.0.dist-info/LICENSE
promypy-0.3.0.dist-info/METADATA
promypy-0.3.0.dist-info/WHEEL
promypy-0.3.0.dist-info/entry_points.txt
promypy-0.3.0.dist-info/top_level.txt
promypy-0.3.0.dist-info/RECORD
