Metadata-Version: 2.1
Name: promypy
Version: 0.3.0
Summary: Progressive type annotation without regression! 🚀
Home-page: https://github.com/Kludex/promypy
Author: Marcelo Trylesinski
Author-email: marcelotryle@email.com
License: MIT
Project-URL: Twitter, https://twitter.com/marcelotryle
Classifier: License :: OSI Approved :: MIT License
Classifier: Intended Audience :: Developers
Classifier: Natural Language :: English
Classifier: Operating System :: OS Independent
Classifier: Programming Language :: Python :: 3 :: Only
Classifier: Programming Language :: Python :: 3
Classifier: Programming Language :: Python :: 3.7
Classifier: Programming Language :: Python :: 3.8
Classifier: Programming Language :: Python :: 3.9
Classifier: Programming Language :: Python :: 3.10
Requires-Python: >=3.7
License-File: LICENSE
Requires-Dist: typer (>=0.6.1)
Requires-Dist: rich (>=12.6.0)
Requires-Dist: pebble (>=5.0.1)
Requires-Dist: mypy
Provides-Extra: test
Requires-Dist: coverage[toml] (>=6.2) ; extra == 'test'
Requires-Dist: pytest (>=6.2.5) ; extra == 'test'
